openfizzbuzz/__init__.py
openfizzbuzz/__main__.py
openfizzbuzz/main.py
openfizzbuzz/config/__init__.py
openfizzbuzz/config/logging_config.py
openfizzbuzz/config/settings.py
openfizzbuzz/core/__init__.py
openfizzbuzz/core/fizzbuzz.py
openfizzbuzz/core/letter.py
openfizzbuzz/core/word.py
tests/__init__.py
tests/test_letter.py
tests/test_word.py
openfizzbuzz-0.1.6.dist-info/LICENSE
openfizzbuzz-0.1.6.dist-info/METADATA
openfizzbuzz-0.1.6.dist-info/WHEEL
openfizzbuzz-0.1.6.dist-info/top_level.txt
openfizzbuzz-0.1.6.dist-info/RECORD
