Metadata-Version: 2.1
Name: openfizzbuzz
Version: 0.1.6
Summary: Open minded fizzbuzz
Home-page: https://github.com/Haytek/openfizzbuzz
Author: Haytek
Author-email: haytek34@gmail.com
License: UNKNOWN
Platform: UNKNOWN
Classifier: Programming Language :: Python :: 3.7
Classifier: License :: OSI Approved :: MIT License
Requires-Python: >=3.6
